<?xml version='1.0' encoding='UTF-8'?>
<kml xmlns='http://www.opengis.net/kml/2.2'>
	<Document>
		<name>Untitled layer</name>
		<Placemark>
			<styleUrl>#line-000000-1</styleUrl>
			<name>Line 1</name>
			<LineString>
				<tessellate>0</tessellate>
				<coordinates>44.54550504684448,40.20832763793229,0.0 44.545687437057495,40.20815557136263,0.0 44.54589128494263,40.20781963061058,0.0 44.546223878860474,40.207057612489095,0.0 44.54612195491791,40.2070166435302,0.0 44.54573035240173,40.206602855657515,0.0 44.54536557197571,40.206348846009206,0.0 44.54448580741882,40.20555608396965,0.0 44.54362750053406,40.20483296218928,0.0 44.54289257526398,40.20417743436275,0.0 44.542683362960815,40.20398487185916,0.0 44.54223275184631,40.20365710463778,0.0 44.54004943370819,40.20491899974589,0.0 44.53803777694702,40.206057962823465,0.0 44.535731077194214,40.20450929611716,0.0 44.533724784851074,40.20287865113559,0.0 44.52767372131348,40.20751646313677,0.0 44.52576398849487,40.20561549023193,0.0 44.516472816467285,40.195880362512945,0.0 44.51641917228699,40.195659093364654,0.0 44.516215324401855,40.19537226191264,0.0 44.516236782073975,40.19499528158771,0.0 44.51638698577881,40.194749423725014,0.0 44.516730308532715,40.19448717435564,0.0 44.519219398498535,40.19357748899523,0.0 44.52130079269409,40.19313493494821,0.0 44.522202014923096,40.19311854400213,0.0 44.52308177947998,40.19326606237435,0.0 44.52404737472534,40.193511925614956,0.0 44.5255708694458,40.193626661488864,0.0 44.52584981918335,40.19359387983041,0.0 44.52601075172424,40.19349553475996,0.0 44.5260751247406,40.19338899410606,0.0 44.52615559101105,40.19262476489379,0.0 44.52615559101105,40.19238914289036,0.0 44.526115357875824,40.19235840952522,0.0 44.52604025602341,40.19235431174216,0.0 44.5260027050972,40.19240143623254,0.0 44.525994658470154,40.19249568511505,0.0 44.52599197626114,40.192645253724976,0.0 44.52587127685547,40.192977171927616,0.0 44.52579885721207,40.1931082996588,0.0 44.525726437568665,40.193169765695515,0.0 44.525495767593384,40.19325581805331,0.0 44.525238275527954,40.19327425783005,0.0 44.5251739025116,40.19325581805331,0.0 44.525096118450165,40.19320049869296,0.0 44.52507197856903,40.19313493494821,0.0 44.525080025196075,40.19307756661956,0.0 44.5251739025116,40.192993562907894,0.0 44.52539384365082,40.19288702146537,0.0 44.525474309921265,40.192835799558424,0.0 44.52552527189255,40.1927722843401,0.0 44.525568187236786,40.19270672018135,0.0 44.52559769153595,40.192602227172365,0.0 44.52560842037201,40.19249568511505,0.0 44.5255708694458,40.19235021395884,0.0 44.525442123413086,40.19209410201004,0.0 44.52543944120407,40.191956825607335,0.0 44.525485038757324,40.19189740737673,0.0 44.52561378479004,40.19181340220324,0.0 44.525825679302216,40.191725299104625,0.0 44.52598124742508,40.19168432088022,0.0 44.526198506355286,40.19165153828288,0.0 44.526434540748596,40.19163719589156,0.0 44.52776223421097,40.19164334263105,0.0 44.52776491641998,40.19155114147992,0.0 44.52779173851013,40.19147738046877,0.0 44.527821242809296,40.19144664669044,0.0 44.52638626098633,40.190213186224575,0.0 44.523746967315674,40.18798798320024,0.0 44.523741602897644,40.1878568455692,0.0 44.52157974243164,40.18600040128128,0.0 44.52139735221863,40.18586106345709,0.0 44.519482254981995,40.18420947862205,0.0 44.51882243156433,40.183668504127326,0.0 44.52082872390747,40.182061948381666,0.0 44.52212691307068,40.180979960828466,0.0 44.52352702617645,40.17996763109166,0.0 44.52338755130768,40.17968893037487,0.0 44.52314615249634,40.17898807498378,0.0 44.52302813529968,40.178483946454094,0.0 44.52276527881622,40.17796341957033,0.0 44.52239513397217,40.17728303982745,0.0 44.52203035354614,40.176774799905445,0.0 44.5215904712677,40.17624606239809,0.0 44.52106475830078,40.17568453045678,0.0 44.520453214645386,40.17511889504443,0.0 44.519750475883484,40.174639330892965,0.0 44.51907455921173,40.17427043308571,0.0 44.518463015556335,40.174012203427445,0.0 44.51776564121246,40.17381955526465,0.0 44.51703608036041,40.17364740112452,0.0 44.51618850231171,40.17349984008542,0.0 44.51529800891876,40.17336867444797,0.0 44.514702558517456,40.17329489366548,0.0 44.51366186141968,40.17320471704465,0.0 44.51358675956726,40.171327376543275,0.0 44.513484835624695,40.17006485634696,0.0 44.51303958892822,40.16507603220481,0.0 44.51282501220703,40.16261222949195,0.0 44.512739181518555,40.16230066071706,0.0 44.512009620666504,40.160189334634815,0.0 44.51142489910126,40.15859862229753,0.0 44.51129615306854,40.15831163414475,0.0 44.51033055782318,40.15559748620685,0.0 44.510255455970764,40.15513418425418,0.0 44.510223269462585,40.15422397121306,0.0 44.51018571853638,40.153613055618266,0.0 44.51016426086426,40.15221079903969,0.0 44.51016426086426,40.15045588744423,0.0 44.509005546569824,40.15025907210099,0.0 44.5050573348999,40.150357479843905,0.0 44.498276710510254,40.15216159652869,0.0 44.4981586933136,40.1518581802566,0.0 44.496989250183105,40.14429693703282,0.0 44.49689269065857,40.14387046440178,0.0 44.49661374092102,40.1432717579216,0.0 44.49638843536377,40.14306672024293,0.0 44.495476484298706,40.1422629665751,0.0 44.495229721069336,40.14224656334002,0.0 44.49509024620056,40.142115337316746,0.0 44.49509024620056,40.14192669946423,0.0 44.491742849349976,40.13922830067829,0.0 44.49135661125183,40.13864595739778,0.0 44.49071288108826,40.137743725557705,0.0 44.490230083465576,40.136890695345905,0.0 44.489758014678955,40.136152487480864,0.0 44.489028453826904,40.13497954071248,0.0 44.48870658874512,40.13470885781388,0.0 44.48132514953613,40.13008247432316,0.0 44.48071360588074,40.12991841238917,0.0 44.47715163230896,40.12904067431575,0.0</coordinates>
			</LineString>
		</Placemark>
		<Style id='line-000000-1'>
			<LineStyle>
				<color>ff000000</color>
				<width>1</width>
			</LineStyle>
		</Style>
	</Document>
</kml>