<?xml version='1.0' encoding='UTF-8'?>
<kml xmlns='http://www.opengis.net/kml/2.2'>
	<Document>
		<name>Untitled layer</name>
		<Placemark>
			<styleUrl>#line-000000-1</styleUrl>
			<name>Line 1</name>
			<LineString>
				<tessellate>0</tessellate>
				<coordinates>44.54927623271942,40.21647981521592,0.0 44.54958200454712,40.215521268361044,0.0 44.54978585243225,40.21498464005618,0.0 44.55002188682556,40.21442752525898,0.0 44.55057978630066,40.213481238893486,0.0 44.55102503299713,40.21245300799316,0.0 44.551180601119995,40.212215406602006,0.0 44.551443457603455,40.211379698539574,0.0 44.5518296957016,40.21042927292503,0.0 44.55185115337372,40.21008924673101,0.0 44.55184042453766,40.209069157913675,0.0 44.55178678035736,40.208335831567574,0.0 44.55199062824249,40.20765985332717,0.0 44.552714824676514,40.20681179836439,0.0 44.55350875854492,40.20562368419506,0.0 44.55372869968414,40.20491899974589,0.0 44.5537394285202,40.204619916340945,0.0 44.553422927856445,40.203620230726195,0.0 44.55281138420105,40.203599745211086,0.0 44.551159143447876,40.20402174557241,0.0 44.55082654953003,40.204046328036746,0.0 44.55060660839081,40.20406271634137,0.0 44.5503169298172,40.20402174557244,0.0 44.5498126745224,40.20396028937254,0.0 44.54936742782593,40.20384966807238,0.0 44.54652428627014,40.202604141716165,0.0 44.54514026641846,40.2020141475604,0.0 44.54099357128143,40.20026052350997,0.0 44.54009234905243,40.19987947303298,0.0 44.53786611557007,40.19919521572557,0.0 44.5376917719841,40.199162436759075,0.0 44.537568390369415,40.199184972300245,0.0 44.53720360994339,40.19937754843747,0.0 44.53418344259262,40.20105334747764,0.0 44.532584846019745,40.20194654373552,0.0 44.52914088964462,40.20384557098372,0.0 44.52763617038727,40.2046731778658,0.0 44.52754765748978,40.20467727490444,0.0 44.52744036912918,40.20469776009391,0.0 44.5260027050972,40.20544136828132,0.0 44.52589273452759,40.20542907730319,0.0 44.52464014291763,40.20410163854895,0.0 44.524460434913635,40.20402379411145,0.0 44.523746967315674,40.20323100488075,0.0 44.519828259944916,40.19919726441047,0.0 44.51686039566994,40.196032996828684,0.0 44.51667934656143,40.1958414355855,0.0 44.51644331216812,40.195698020396776,0.0 44.51629847288132,40.19547675065352,0.0 44.51625555753708,40.195318993080825,0.0 44.516231417655945,40.195130503032274,0.0 44.51627433300018,40.19498503752791,0.0 44.516346752643585,40.194862108689385,0.0 44.516462087631226,40.19472893552953,0.0 44.51652109622955,40.19467771501382,0.0 44.51667129993439,40.194575273866285,0.0 44.51679736375809,40.19450766262412,0.0 44.5184201002121,40.19386432803873,0.0 44.51871782541275,40.19375369026568,0.0 44.519487619400024,40.19354265845737,0.0 44.520311057567596,40.19333982144012,0.0 44.520579278469086,40.1933090885058,0.0 44.52103525400162,40.193204596424906,0.0 44.521209597587585,40.193177961162846,0.0 44.52148586511612,40.193149277022805,0.0 44.52190965414047,40.19314313041977,0.0 44.52234148979187,40.19317591229611,0.0 44.52267408370972,40.193227133946166,0.0 44.52326148748398,40.19335416347135,0.0 44.52388644218445,40.19347914390102,0.0 44.524251222610474,40.19353651189,0.0 44.52506124973297,40.19361231951524,0.0 44.525562822818756,40.193653296574674,0.0 44.525742530822754,40.19364305231213,0.0 44.525847136974335,40.19361231951524,0.0 44.52595978975296,40.19353446303408,0.0 44.526067078113556,40.19340333612691,0.0 44.526067078113556,40.1932209873502,0.0 44.52613413333893,40.192710817943144,0.0 44.52616631984711,40.19258788498208,0.0 44.526342675089836,40.192365068422184,0.0 44.52664006501436,40.192167606238314,0.0 44.52698724344373,40.192023799110906,0.0 44.527321765199304,40.19194369981734,0.0 44.527676780708134,40.191952823842364,0.0 44.52801882260246,40.19205635142715,0.0 44.52840377984103,40.19204514049844,0.0 44.52857952477643,40.1919273866178,0.0 44.52842267579399,40.19175226308291,0.0 44.52846431027865,40.19158123692584,0.0 44.528409385238774,40.191426601696506,0.0 44.528198892076034,40.19132933597062,0.0 44.527945483569056,40.19135500552397,0.0 44.52695330721326,40.190523370283735,0.0 44.52411900332663,40.18808980598519,0.0 44.52368937709252,40.18843624663106,0.0 44.523243657604326,40.18875399950844,0.0 44.522768433816964,40.18905535896913,0.0 44.522250294685364,40.189319835402024,0.0 44.52181041240692,40.18953907625762,0.0 44.52124983072281,40.18980339373008,0.0 44.52080458402634,40.19001033924927,0.0 44.51974779367447,40.190397592039325,0.0 44.51947420835495,40.19046315843039,0.0 44.51934680342674,40.1904590605328,0.0 44.519271701574326,40.19045188921143,0.0 44.519203305244446,40.190438571041156,0.0 44.51911345124245,40.190410910217615,0.0 44.51895922422409,40.19033919691889,0.0 44.51878756284714,40.19018859874471,0.0 44.51742768287659,40.18905346705383,0.0 44.5164030790329,40.18819288524116,0.0 44.5155394077301,40.18747572538985,0.0 44.515322148799896,40.18734048868244,0.0 44.5152148604393,40.18731590016121,0.0 44.51514780521393,40.18728516449714,0.0 44.51509952545166,40.18723496288257,0.0 44.51506868004799,40.18717246694309,0.0 44.51504588127136,40.18709562759433,0.0 44.514945298433304,40.18697678256349,0.0 44.5147830247879,40.186858961853254,0.0 44.5139542222023,40.18615613145193,0.0 44.51314017176628,40.185465588367755,0.0 44.51229527592659,40.18475249792411,0.0 44.51109766960144,40.183757642267054,0.0 44.50952589511871,40.182429779235086,0.0 44.508890211582184,40.18193694691338,0.0 44.50772076845169,40.18092053298188,0.0 44.506841003894806,40.180227887344984,0.0 44.50590223073959,40.17944711559011,0.0 44.50473815202713,40.17844296023011,0.0 44.50463354587555,40.17833229730175,0.0 44.50419098138809,40.178141710724255,0.0 44.50359284877777,40.17763962524229,0.0 44.50339436531067,40.17733017478862,0.0 44.50381278991699,40.176848576904504,0.0 44.504494071006775,40.17588127210372,0.0 44.505397975444794,40.17479713656478,0.0 44.505765438079834,40.1742991252093,0.0 44.50782537460327,40.171798766049655,0.0 44.50837254524231,40.171114225430664,0.0 44.50861394405365,40.17094206442794,0.0 44.51006770133972,40.17165530002475,0.0 44.5101535320282,40.17175777578779,0.0 44.51157510280609,40.172364429135506,0.0 44.51178431510925,40.17235828064904,0.0 44.5118647813797,40.1723746766117,0.0 44.51318979263306,40.17295058228667,0.0 44.51331585645676,40.172955705980726,0.0 44.51338291168213,40.17295006991725,0.0 44.51342046260834,40.17294135963643,0.0 44.513506293296814,40.17288961029796,0.0 44.51366722583771,40.17272616410836,0.0 44.51358072459698,40.1713202031994,0.0 44.51345130801201,40.16969798324982,0.0 44.51343923807144,40.16944793452767,0.0 44.51342046260834,40.169194810497736,0.0 44.51332926750183,40.168240719131056,0.0 44.51314687728882,40.166519016564145,0.0 44.51303958892822,40.16505963447901,0.0 44.51285719871521,40.16309187862673,0.0 44.51280355453491,40.162587632009085,0.0 44.512728452682495,40.162284262320874,0.0 44.51253533363342,40.16175541192032,0.0 44.511982798576355,40.16018113518225,0.0 44.51166093349457,40.15932428692969,0.0 44.51140344142914,40.158606821941234,0.0 44.51030373573303,40.15558928619978,0.0 44.510239362716675,40.155146484346865,0.0 44.510212540626526,40.15486358165143,0.0 44.51010525226593,40.151312847603315,0.0 44.51007843017578,40.15047228869707,0.0 44.510014057159424,40.14579777134824,0.0 44.51102256774902,40.14251721621253,0.0 44.51027154922485,40.135168197852686,0.0 44.509230852127075,40.12456977645716,0.0</coordinates>
			</LineString>
		</Placemark>
		<Style id='line-000000-1'>
			<LineStyle>
				<color>ff000000</color>
				<width>1</width>
			</LineStyle>
		</Style>
	</Document>
</kml>